didww_encrypt/Encrypt.py
didww_encrypt/__init__.py
didww_encrypt/__main__.py
didww_encrypt/command_line.py
didww_encrypt/encryption.py
didww_encrypt/fetching.py
didww_encrypt/fingerprint.py
didww_encrypt-1.0.0.dist-info/METADATA
didww_encrypt-1.0.0.dist-info/WHEEL
didww_encrypt-1.0.0.dist-info/entry_points.txt
didww_encrypt-1.0.0.dist-info/top_level.txt
didww_encrypt-1.0.0.dist-info/RECORD
