Metadata-Version: 2.1
Name: didww-encrypt
Version: 1.0.0
Summary: File encryption for DIDWW API 3
Home-page: https://github.com/didww/didww_encrypt_python
Author: Denis Talakevich
Author-email: senid231@gmail.com
License: MIT
Project-URL: Bug Tracker, https://github.com/didww/didww_encrypt_python/issues
Keywords: DIDWW,encryption
Platform: UNKNOWN
Classifier: Programming Language :: Python :: 3
Classifier: License :: OSI Approved :: MIT License
Classifier: Operating System :: OS Independent
Requires-Python: >=3.6
Requires-Dist: pycryptodomex
